mm_cli/__init__.py
mm_cli/__main__.py
mm_cli/client.py
mm_cli/gateway.py
mm_cli/hemicarp-future.py
mm_cli/util.py
mm_cli-0.0.5.dist-info/LICENSE
mm_cli-0.0.5.dist-info/METADATA
mm_cli-0.0.5.dist-info/WHEEL
mm_cli-0.0.5.dist-info/top_level.txt
mm_cli-0.0.5.dist-info/RECORD
