Metadata-Version: 2.1
Name: mm-cli
Version: 0.0.5
Summary: A CLI application for connecting to the mesh. Written in Python.
Home-page: https://github.com/MassMesh/mm-cli
Author: Mass Mesh Technology Club
Author-email: support@massmesh.org
License: UNKNOWN
Platform: UNKNOWN
Classifier: Programming Language :: Python :: 3
Classifier: License :: OSI Approved :: GNU General Public License v3 (GPLv3)
Classifier: Operating System :: OS Independent
Requires-Python: >=3.6
Requires-Dist: argh
Requires-Dist: netaddr
